{
    "name": "SP814 Motion Detector", 
    "type": "Multicapteurs", 
    "comlink": "857-everspring-detecteur-de-presence-z-wave-sp814-3700946500288", 
    "remark": "", 
    "imglink": "everspring.sp814", 
    "commands": [
        {
            "name": "Présence", 
            "type": "info", 
            "isVisible": 1, 
            "isHistorized": 1, 
            "configuration": {
                "class": 48, 
                "value": "", 
                "index": 0, 
                "instance": 1
            }, 
            "subtype": "binary", 
            "display": {
                "generic_type": "PRESENCE"
            }, 
            "unite": ""
        }, 
        {
            "name": "Batterie", 
            "type": "info", 
            "isVisible": 0, 
            "isHistorized": 1, 
            "configuration": {
                "class": 128, 
                "value": "", 
                "index": 0, 
                "instance": 1, 
                "minValue": 0, 
                "maxValue": 100
            }, 
            "subtype": "numeric", 
            "display": {
                "generic_type": "BATTERY"
            }, 
            "unite": "%"
        }
    ]
}