{		
		"name": "MultiSensor 4in1 (DSB05) ",
        "doc" : "",
        "type": "Multicapteurs",
        "comlink" : "2681-aeon-labs-detecteur-multifonction-multisensor-z-wave-plus-gen5-1220000012684",
        "remark" : "Attention ce module peut remonter de mauvaises données, il faut bien faire attention à la configuration. Remplacé en boutique par son équivalent Gen5",
        "imglink" : "aeotec.multisensor",
        "battery_type" : "2x1.5V AAA",
		"configuration" : {
        "conf_version" : 1
		},
        "commands": [
            {
                "name": "Présence",
                "type": "info",
                "subtype": "binary",
                "isVisible": 1,
                "isHistorized": 1,
                "configuration": {
                    "class": "0x30",
                    "value": "data[0].val"
                },
                "display": {
                    "invertBinary": "1"
					"generic_type": "PRESENCE"
                },
                "template": {
                    "dashboard": "presence",
                    "mobile": "presence"
                }
            },
            {
                "name": "Température",
                "type": "info",
                "subtype": "numeric",
                "isVisible": 1,
                "isHistorized": 1,
                "unite": "°C",
				"display": {
                    		"generic_type": "TEMPERATURE"
                	},
                "configuration": {
                    "class": "0x31",
                    "value": "data[1].val"
                }
            },
            {
                "name": "Luminosité",
                "type": "info",
                "subtype": "numeric",
                "isVisible": 1,
                "isHistorized": 1,
                "unite": "Lux",
				"display": {
                    		"generic_type": "BRIGHTNESS"
                	},
                "configuration": {
                    "class": "0x31",
                    "value": "data[3].val",
                    "maxValue": 1000,
                    "minValue": 0
                }
            },
            {
                "name": "Humidité",
                "type": "info",
                "subtype": "numeric",
                "isVisible": 1,
                "isHistorized": 1,
                "unite": "%",
				"display": {
                    		"generic_type": "HUMIDITY"
                	},
                "configuration": {
                    "class": "0x31",
                    "value": "data[5].val"
                }
            },
            {
                "name": "Batterie",
                "type": "info",
                "subtype": "numeric",
                "isVisible": 0,
                "isHistorized": 0,
                "unite": "%",
				"display": {
                    		"generic_type": "BATTERY"
                	},
                "configuration": {
                    "class": "0x80",
                    "value": "data[0].val"
                }
            }
        ]
    }