{
    "name": "TZ68e",
    "doc" : "",
    "type": "Prise",
    "comlink" : "",
    "remark" : "Vendu aussi sous la marque TkbHome",
    "imglink" : "tkb.tz68e",
    "configuration" : {
        "conf_version" : 1
    },
    "commands": [
        {
            "name": "On",
            "type": "action",
            "subtype": "other",
            "isVisible": 1,
            "configuration": {
                "class": "0x25",
                "instanceId": 0,
                "value": "data[0].Set(255)"
            }
        },
        {
            "name": "Off",
            "type": "action",
            "subtype": "other",
            "isVisible": 1,
            "configuration": {
                "class": "0x25",
                "instanceId": 0,
                "value": "data[0].Set(0)"
            }
        },
        {
            "name": "Etat",
            "type": "info",
            "subtype": "binary",
            "isVisible": 1,
            "configuration": {
                "class": "0x25",
                "instanceId": 0,
                "value": "data[0].val"
            }
        }
    ]
}
